README.rst
setup.py
httpnext/__init__.py
httpnext.egg-info/PKG-INFO
httpnext.egg-info/SOURCES.txt
httpnext.egg-info/dependency_links.txt
httpnext.egg-info/top_level.txt